ferment_ng-0.0.2-py3.5-nspkg.pth
ferment_ng/scripts.py
ferment_ng/templates.py
ferment_ng-0.0.2.dist-info/METADATA
ferment_ng-0.0.2.dist-info/RECORD
ferment_ng-0.0.2.dist-info/WHEEL
ferment_ng-0.0.2.dist-info/entry_points.txt
ferment_ng-0.0.2.dist-info/namespace_packages.txt
ferment_ng-0.0.2.dist-info/top_level.txt
