Metadata-Version: 2.1
Name: ferment-ng
Version: 0.0.2
Summary: A tool to provide the current docker config in ferm format
Home-page: UNKNOWN
Author: Olga Ukhina
Author-email: olga.uhina@gmail.com
License: Apache Version 2
Keywords: ferm docker iptables
Platform: UNKNOWN
Classifier: Development Status :: 3 - Alpha
Classifier: Intended Audience :: Developers
Classifier: License :: OSI Approved :: Apache Software License
Classifier: Operating System :: OS Independent
Requires-Dist: docker-py
Requires-Dist: click
Requires-Dist: wheezy.template
